{
    "details": {
        "base_dict": {
            "d": 16,
            "e": 16,
            "id": 10,
            "n": 16,
            "p": 16,
            "q": 16,
            "t": 10
        },
        "bitlen": 1024,
        "category": "Library",
        "compressed": true,
        "fips_mode": false,
        "format": "json",
        "header": null,
        "name": "Libgcrypt",
        "public_only": false,
        "separator": null,
        "version": "1.6.5"
    },
    "files": [
        {
            "name": "a86c28e1772e068f.json.gz",
            "records": 2190000,
            "sha256": "a86c28e1772e068f8775471f5a5d1b0da0f2f1b23d44b8313a92fac51f16ec85"
        }
    ],
    "type": "reference"
}