{
    "details": {
        "base_dict": {
            "d": 16,
            "e": 16,
            "id": 10,
            "n": 16,
            "p": 16,
            "q": 16,
            "t": 10
        },
        "bitlen": 1024,
        "category": "Library",
        "compressed": true,
        "fips_mode": false,
        "format": "json",
        "header": null,
        "name": "OpenSSL",
        "public_only": false,
        "separator": null,
        "version": "1.0.2g 8-bit"
    },
    "files": [
        {
            "name": "d3e5623a1ef8b9e8.json.gz",
            "records": 1090000,
            "sha256": "d3e5623a1ef8b9e8e89d36e24850a69553947af15f07b83e1f2c9f55b2b0c6ec"
        }
    ],
    "type": "reference"
}